{
  "header": {
    "schema": "studio_catalogue_lookup_work_detail_record_v1"
  },
  "work_detail": {
    "detail_uid": "01196-044",
    "work_id": "01196",
    "detail_id": "044",
    "project_subfolder": "forms",
    "project_filename": "form 43.jpg",
    "title": "form 43",
    "status": "published",
    "published_date": "2026-03-23",
    "width_px": 2000,
    "height_px": 2000
  },
  "record_hash": "c17cef02af3d96c28b8a93754820503573c4077011e232e23c622d9a825cc0fc",
  "work_summary": {
    "work_id": "01196",
    "title": "forms"
  }
}
