{
  "header": {
    "schema": "work_record_v3",
    "version": "blake2b-839e3253cd415928273c8e079472acb5",
    "generated_at_utc": "2026-06-16T19:13:01Z",
    "work_id": "00116",
    "count": 0
  },
  "work": {
    "work_id": "00116",
    "title": "learning to draw landscapes 3",
    "year": 2010,
    "year_display": "c. 2010?",
    "series_ids": [
      "089"
    ],
    "medium_type": "drawing",
    "medium_caption": "pencil on paper",
    "height_cm": 29.7,
    "width_cm": 20.5,
    "width_px": 2480,
    "height_px": 3508
  },
  "sections": []
}
