{
  "doc_id": "site-request-work-detail-section-data-model",
  "title": "Work Detail Section Data Model Request",
  "added_date": "2026-06-16",
  "last_updated": "2026-06-16",
  "source_path": "site-request-work-detail-section-data-model.md",
  "viewer_url": "/docs/?scope=studio&doc=site-request-work-detail-section-data-model",
  "parent_id": "change-requests",
  "ui_status": "draft",
  "content_html": "<h1>Work Detail Section Data Model Request</h1>\n<p>Status:</p>\n<ul>\n<li>proposed</li>\n</ul>\n<h2>Summary</h2>\n<p>Replace the current work-detail section metadata model before moving detail editing into modals on the work editor page.</p>\n<p>The current canonical work-detail source and generated Studio lookup payloads mix section-level metadata with detail-record metadata. That makes the current work detail editor appear to edit one record, while it is often editing section attributes that are shared by multiple details.</p>\n<p>This request separates:</p>\n<ul>\n<li>work detail section metadata</li>\n<li>individual work detail metadata</li>\n<li>generated lookup projection shape</li>\n<li>public work JSON section/detail ordering rules</li>\n</ul>\n<p>This is a data-model and generation change first. The modal UI migration should happen after this model boundary is stable.</p>\n<h2>Current Problem</h2>\n<p>Example generated lookup payload from <code>studio/data/generated/catalogue-lookup/works/00782.json</code>:</p>\n<pre><code class=\"language-json\">{\n  &quot;detail_sections&quot;: [\n    {\n      &quot;section_id&quot;: &quot;00782-1&quot;,\n      &quot;section_title&quot;: &quot;details&quot;,\n      &quot;sort_order&quot;: null,\n      &quot;count&quot;: 4,\n      &quot;details&quot;: [\n        {\n          &quot;detail_uid&quot;: &quot;00782-001&quot;,\n          &quot;detail_id&quot;: &quot;001&quot;,\n          &quot;title&quot;: &quot;birth of forms - detail 1&quot;,\n          &quot;section_id&quot;: &quot;00782-1&quot;,\n          &quot;section_title&quot;: &quot;details&quot;,\n          &quot;sort_order&quot;: null,\n          &quot;details_subfolder&quot;: &quot;details&quot;,\n          &quot;project_filename&quot;: &quot;birth of forms - detail 1.jpg&quot;\n        }\n      ]\n    }\n  ]\n}\n</code></pre>\n<p>Problems:</p>\n<ul>\n<li><code>section_id</code>, <code>section_title</code>, <code>sort_order</code>, and <code>details_subfolder</code> are repeated for every nested detail even though <code>details[]</code> is already nested inside a section.</li>\n<li><code>details_subfolder</code> is section-level source media organization, but it is not present on the section object in the Studio work lookup.</li>\n<li>The name <code>sort_order</code> is ambiguous. In current active code it means section ordering, but the detail list itself also needs a section-level sorting mode.</li>\n<li>The current work detail editor mixes section editing and detail editing in one form.</li>\n</ul>\n<h2>Confirmed Current Behavior</h2>\n<p>Active implementation currently treats work-detail <code>sort_order</code> as section order:</p>\n<ul>\n<li><code>studio/services/catalogue/catalogue_lookup.py</code> uses it to sort <code>detail_sections</code>.</li>\n<li><code>studio/services/catalogue/catalogue_generation_records.py</code> uses it to sort public work JSON <code>sections[]</code>.</li>\n<li><code>studio/app/frontend/js/catalogue-work-detail-fields.js</code> labels it as section sort order.</li>\n<li>source validation requires it to be a whole number when present.</li>\n</ul>\n<p>Active detail ordering is always by <code>detail_id</code>.</p>\n<p>Existing canonical detail data currently has no non-null <code>sort_order</code> values, so removing detail-level <code>sort_order</code> does not discard active ordering data.</p>\n<h2>Target Canonical Model</h2>\n<p>Introduce a dedicated section source map and remove section metadata from detail records.</p>\n<p>Target canonical source shape for <code>studio/data/canonical/catalogue/work_details.json</code>:</p>\n<pre><code class=\"language-json\">{\n  &quot;header&quot;: {\n    &quot;schema&quot;: &quot;catalogue_source_work_details_v2&quot;\n  },\n  &quot;work_detail_sections&quot;: {\n    &quot;00782-1&quot;: {\n      &quot;section_id&quot;: &quot;00782-1&quot;,\n      &quot;work_id&quot;: &quot;00782&quot;,\n      &quot;details_subfolder&quot;: &quot;details&quot;,\n      &quot;section_title&quot;: &quot;details&quot;,\n      &quot;section_order&quot;: null,\n      &quot;detail_sort&quot;: null\n    }\n  },\n  &quot;work_details&quot;: {\n    &quot;00782-001&quot;: {\n      &quot;detail_uid&quot;: &quot;00782-001&quot;,\n      &quot;work_id&quot;: &quot;00782&quot;,\n      &quot;detail_id&quot;: &quot;001&quot;,\n      &quot;section_id&quot;: &quot;00782-1&quot;,\n      &quot;title&quot;: &quot;birth of forms - detail 1&quot;,\n      &quot;project_filename&quot;: &quot;birth of forms - detail 1.jpg&quot;\n    }\n  }\n}\n</code></pre>\n<p>Section fields:</p>\n<ul>\n<li><code>section_id</code>: stable generated section key, scoped to the parent work.</li>\n<li><code>work_id</code>: parent work id.</li>\n<li><code>details_subfolder</code>: source-image subfolder under the parent work <code>project_folder</code>.</li>\n<li><code>section_title</code>: public section label.</li>\n<li><code>section_order</code>: optional numeric section order.</li>\n<li><code>detail_sort</code>: optional section-level detail sort mode.</li>\n</ul>\n<p>Detail fields:</p>\n<ul>\n<li><code>detail_uid</code>: stable detail identity and route/edit target.</li>\n<li><code>work_id</code>: parent work id.</li>\n<li><code>detail_id</code>: local detail suffix, retained for display and efficient sorting/filtering.</li>\n<li><code>section_id</code>: foreign key to <code>work_detail_sections</code>.</li>\n<li><code>title</code>: detail title.</li>\n<li><code>project_filename</code>: source detail image filename.</li>\n<li>generated or media-maintained dimensions such as <code>width_px</code> and <code>height_px</code>.</li>\n</ul>\n<p>Removed from detail records:</p>\n<ul>\n<li><code>details_subfolder</code></li>\n<li><code>section_title</code></li>\n<li><code>sort_order</code></li>\n</ul>\n<h2>Ordering Semantics</h2>\n<h3>Section Order</h3>\n<p><code>section_order</code> replaces the current section use of <code>sort_order</code>.</p>\n<p>Rules:</p>\n<ul>\n<li>numeric values sort sections explicitly, ascending</li>\n<li><code>null</code> means use the current fallback: sort by <code>section_id</code></li>\n<li><code>section_order</code> is section metadata, not detail metadata</li>\n</ul>\n<h3>Detail Sort</h3>\n<p><code>detail_sort</code> is a section-level sort mode.</p>\n<p>Allowed values:</p>\n<ul>\n<li><code>detail_id</code></li>\n<li><code>title</code></li>\n<li><code>null</code></li>\n</ul>\n<p>Rules:</p>\n<ul>\n<li><code>null</code> means <code>detail_id</code></li>\n<li><code>detail_id</code> preserves current behavior</li>\n<li><code>title</code> sorts details by normalized title with <code>detail_id</code> or <code>detail_uid</code> as a deterministic tie-breaker</li>\n<li>the value belongs to the section because it controls the whole detail list inside that section</li>\n</ul>\n<h2>Target Studio Work Lookup Projection</h2>\n<p>Generated <code>studio/data/generated/catalogue-lookup/works/&lt;work_id&gt;.json</code> should project section metadata once per section.</p>\n<p>Target generated lookup shape for <code>studio/data/generated/catalogue-lookup/works/00782.json</code>:</p>\n<pre><code class=\"language-json\">{\n  &quot;detail_sections&quot;: [\n    {\n      &quot;section_id&quot;: &quot;00782-1&quot;,\n      &quot;details_subfolder&quot;: &quot;details&quot;,\n      &quot;section_title&quot;: &quot;details&quot;,\n      &quot;section_order&quot;: null,\n      &quot;detail_sort&quot;: null,\n      &quot;count&quot;: 4,\n      &quot;details&quot;: [\n        {\n          &quot;detail_uid&quot;: &quot;00782-001&quot;,\n          &quot;detail_id&quot;: &quot;001&quot;,\n          &quot;title&quot;: &quot;birth of forms - detail 1&quot;,\n          &quot;project_filename&quot;: &quot;birth of forms - detail 1.jpg&quot;\n        }\n      ]\n    }\n  ]\n}\n</code></pre>\n<p>Nested detail rows should not repeat:</p>\n<ul>\n<li><code>section_id</code></li>\n<li><code>section_title</code></li>\n<li><code>section_order</code></li>\n<li><code>detail_sort</code></li>\n<li><code>details_subfolder</code></li>\n</ul>\n<p><code>detail_uid</code> remains the identity field. <code>detail_id</code> remains as display and sorting metadata.</p>\n<p>Focused work-detail lookup records may still expose the joined section metadata if the standalone work detail editor needs it during the transition, but that should be treated as a temporary route compatibility surface. The target modal UI should load section metadata from the parent work lookup or a section-focused service response.</p>\n<h2>Generation And Publishing Changes</h2>\n<h3>Catalogue Source Loader And Validation</h3>\n<p>Update <code>studio/services/catalogue/catalogue_source.py</code> to:</p>\n<ul>\n<li>parse and normalize <code>work_detail_sections</code></li>\n<li>validate each section has <code>section_id</code>, <code>work_id</code>, and <code>section_title</code></li>\n<li>validate each detail <code>section_id</code> references a section for the same <code>work_id</code></li>\n<li>validate <code>section_order</code> as a whole number when present</li>\n<li>validate <code>detail_sort</code> as <code>detail_id</code>, <code>title</code>, or empty/null</li>\n<li>reject detail-level <code>sort_order</code></li>\n<li>reject detail-level <code>section_title</code> and <code>details_subfolder</code> after migration</li>\n</ul>\n<h3>Source Mutation And Write Services</h3>\n<p>Update create/save planning so section writes are explicit:</p>\n<ul>\n<li>creating a new section generates the next <code>section_id</code> for that work</li>\n<li>creating a detail requires a target <code>section_id</code></li>\n<li>moving a detail between sections changes only the detail <code>section_id</code></li>\n<li>editing <code>details_subfolder</code>, <code>section_title</code>, <code>section_order</code>, or <code>detail_sort</code> updates the section record</li>\n<li>editing <code>title</code> or <code>project_filename</code> updates the detail record</li>\n</ul>\n<p>Affected services:</p>\n<ul>\n<li><code>studio/services/catalogue/catalogue_source_mutation.py</code></li>\n<li><code>studio/services/catalogue/catalogue_work_detail_service.py</code></li>\n<li><code>studio/services/catalogue/catalogue_bulk_service.py</code></li>\n<li><code>studio/services/catalogue/catalogue_workbook_import.py</code></li>\n<li><code>studio/services/catalogue/validate_catalogue_source.py</code></li>\n</ul>\n<h3>Lookup Export</h3>\n<p>Update <code>studio/services/catalogue/catalogue_lookup.py</code> so:</p>\n<ul>\n<li>work lookup <code>detail_sections[]</code> joins section records with details</li>\n<li>nested detail summaries contain only detail identity and detail-owned fields</li>\n<li>section sorting uses <code>section_order</code>, falling back to <code>section_id</code></li>\n<li>detail sorting uses section <code>detail_sort</code>, falling back to <code>detail_id</code></li>\n<li>work-detail search and focused lookup records preserve the fields needed by the current editor during transition</li>\n</ul>\n<p>Regenerate:</p>\n<ul>\n<li><code>studio/data/generated/catalogue-lookup/work_search.json</code></li>\n<li><code>studio/data/generated/catalogue-lookup/work_detail_search.json</code></li>\n<li><code>studio/data/generated/catalogue-lookup/works/*.json</code></li>\n<li><code>studio/data/generated/catalogue-lookup/work_details/*.json</code></li>\n</ul>\n<h3>Public Work JSON</h3>\n<p>Update public work JSON generation:</p>\n<ul>\n<li><code>studio/services/catalogue/generate_work_pages.py</code></li>\n<li><code>studio/services/catalogue/catalogue_generation_records.py</code></li>\n</ul>\n<p>Public <code>site/assets/works/index/&lt;work_id&gt;.json</code> should keep its existing nested section shape, but use the new section source map:</p>\n<ul>\n<li>each section carries <code>section_id</code>, <code>section_title</code>, <code>section_order</code>, optional <code>detail_sort</code>, and <code>details[]</code></li>\n<li>nested public detail rows do not repeat section metadata</li>\n<li>section order uses <code>section_order</code> with <code>section_id</code> fallback</li>\n<li>detail order uses <code>detail_sort</code> with <code>detail_id</code> fallback</li>\n</ul>\n<p>Example target public payload shape for <code>site/assets/works/index/00782.json</code>:</p>\n<pre><code class=\"language-json\">{\n  &quot;sections&quot;: [\n    {\n      &quot;section_id&quot;: &quot;00782-1&quot;,\n      &quot;section_title&quot;: &quot;details&quot;,\n      &quot;section_order&quot;: null,\n      &quot;detail_sort&quot;: null,\n      &quot;details&quot;: [\n        {\n          &quot;detail_uid&quot;: &quot;00782-001&quot;,\n          &quot;detail_id&quot;: &quot;001&quot;,\n          &quot;title&quot;: &quot;birth of forms - detail 1&quot;\n        }\n      ]\n    }\n  ]\n}\n</code></pre>\n<p>Decide during implementation whether public payloads should expose the field as <code>section_order</code> or continue projecting a compatibility <code>sort_order</code>. Prefer <code>section_order</code> for new schema clarity unless a public runtime compatibility concern requires a staged switch.</p>\n<h3>Public Runtime</h3>\n<p>Review the public catalogue runtime after payload generation changes:</p>\n<ul>\n<li><code>site/assets/js/catalogue/routes/work-page.js</code></li>\n<li><code>site/assets/js/catalogue/routes/work-detail-page.js</code></li>\n</ul>\n<p>The public runtime should render details in generated order and should not need to sort detail rows itself. If route code currently derives section ids or labels from nested detail fallback fields, remove those fallbacks after payload migration.</p>\n<h2>Studio Editor Changes</h2>\n<h3>Current Work Editor</h3>\n<p><code>/studio/catalogue-work/</code> currently includes the detail navigation/browser surface.</p>\n<p>Before modal editing:</p>\n<ul>\n<li>update <code>catalogue-work-detail-browser.js</code> to read section-level <code>details_subfolder</code>, <code>section_order</code>, and <code>detail_sort</code></li>\n<li>ensure nested detail rows no longer depend on repeated <code>section_id</code>, <code>section_title</code>, or <code>details_subfolder</code></li>\n<li>keep <code>detail_uid</code> as the edit identity</li>\n<li>keep <code>detail_id</code> for display, filtering, and local sort affordances</li>\n</ul>\n<p>Future modal UI:</p>\n<ul>\n<li>section modal edits <code>details_subfolder</code>, <code>section_title</code>, <code>section_order</code>, and <code>detail_sort</code></li>\n<li>detail modal edits <code>detail_id</code>, <code>title</code>, <code>project_filename</code>, and selected <code>section_id</code></li>\n<li>detail move workflows should change only the detail <code>section_id</code></li>\n<li>section delete workflows must define what happens to contained details before implementation</li>\n</ul>\n<h3>Current Work Detail Editor</h3>\n<p><code>/studio/catalogue-work-detail/</code> is transitional.</p>\n<p>During the model migration it should either:</p>\n<ul>\n<li>continue to work through joined focused lookup payloads while section fields are visibly read-only or removed, or</li>\n<li>be narrowed to detail-owned fields only and link users back to the parent work editor for section changes</li>\n</ul>\n<p>The target direction is to retire this standalone page once work-detail modals exist on the work editor.</p>\n<p>Do not add new section-editing behavior to the standalone work detail editor unless it is required as a temporary migration bridge.</p>\n<h2>Workbook Import</h2>\n<p>Current detail ordering has historically been handled before import: Excel rows were manually sorted and assigned sequential detail ids.</p>\n<p>The import path should preserve that behavior:</p>\n<ul>\n<li>detail ids remain the stable imported order inside a section when <code>detail_sort</code> is empty or <code>detail_id</code></li>\n<li>import may create section records from <code>details_subfolder</code> plus <code>section_title</code></li>\n<li>import may accept <code>section_order</code> and <code>detail_sort</code> when present</li>\n<li>import should reject or ignore legacy detail-level <code>sort_order</code> according to the migration policy</li>\n</ul>\n<h2>Migration Plan</h2>\n<ol>\n<li>Add source model support for <code>work_detail_sections</code> while reading current detail-level section fields.</li>\n<li>Write a one-time migration that extracts unique section records from current <code>work_details</code>.</li>\n<li>Rename current section <code>sort_order</code> values to section <code>section_order</code>; existing values are all null in current canonical data.</li>\n<li>Set migrated section <code>detail_sort</code> to null.</li>\n<li>Remove <code>details_subfolder</code>, <code>section_title</code>, and <code>sort_order</code> from detail records.</li>\n<li>Update validators and mutation planners to reject the old detail-level fields after migration.</li>\n<li>Update lookup export and public work JSON generation.</li>\n<li>Regenerate Studio lookup payloads and public catalogue artifacts as required.</li>\n<li>Update Studio work editor detail browser to consume the new lookup shape.</li>\n<li>Narrow or retire the standalone work detail editor after modal editing exists.</li>\n</ol>\n<h2>Tests And Verification</h2>\n<p>Required focused tests:</p>\n<ul>\n<li>source validation accepts migrated section/detail records</li>\n<li>source validation rejects detail-level <code>sort_order</code></li>\n<li>source validation rejects mismatched detail <code>section_id</code> / <code>work_id</code></li>\n<li>lookup export projects section metadata once per section</li>\n<li>lookup export strips section metadata from nested detail summaries</li>\n<li>public work JSON section ordering uses <code>section_order</code> with <code>section_id</code> fallback</li>\n<li>public work JSON detail ordering uses <code>detail_sort</code> with <code>detail_id</code> fallback</li>\n<li>workbook import creates or resolves section records correctly</li>\n<li>current work editor detail browser works with the new lookup shape</li>\n<li>standalone work detail editor either works with joined payloads or no longer exposes section fields</li>\n</ul>\n<p>Suggested commands:</p>\n<pre><code class=\"language-bash\">$HOME/miniconda3/bin/python3 studio/tests/python/test_catalogue_source_media_section_schema.py\n$HOME/miniconda3/bin/python3 studio/tests/python/test_catalogue_source_mutation.py\n$HOME/miniconda3/bin/python3 studio/tests/python/test_catalogue_lookup_dependencies.py\n$HOME/miniconda3/bin/python3 studio/tests/python/test_catalogue_generation_records.py\n$HOME/miniconda3/bin/python3 studio/services/catalogue/verify_catalogue_field_registry.py\n</code></pre>\n<p>Add or update focused smoke coverage for:</p>\n<ul>\n<li><code>studio/tests/smoke/catalogue_work_editor_state_modules.py</code></li>\n<li>any modal smoke introduced by the later work-editor detail modal implementation</li>\n</ul>\n<h2>Documentation Follow-Up</h2>\n<p>Update these stable docs after implementation:</p>\n<ul>\n<li><a href=\"/docs/?scope=studio&amp;doc=data-models-catalogue-source\">Catalogue Source Model</a></li>\n<li><a href=\"/docs/?scope=studio&amp;doc=scripts-catalogue-lookup\">Catalogue Lookup Export</a></li>\n<li><a href=\"/docs/?scope=studio&amp;doc=catalogue-work-editor\">Catalogue Work Editor</a></li>\n<li><a href=\"/docs/?scope=studio&amp;doc=catalogue-work-detail-editor\">Catalogue Work Detail Editor</a></li>\n<li><a href=\"/docs/?scope=studio&amp;doc=scripts-catalogue-write-server-build-lookup\">Catalogue Write Server</a></li>\n<li><a href=\"/docs/?scope=studio&amp;doc=scripts-build-catalogue-json\">Scoped JSON Catalogue Build</a></li>\n</ul>\n<h2>Open Questions</h2>\n<ul>\n<li>Should the migrated source keep sections inside <code>work_details.json</code>, or should sections move to a separate <code>work_detail_sections.json</code> file?</li>\n<li>Should public work JSON expose <code>section_order</code>, or project a temporary <code>sort_order</code> compatibility alias?</li>\n<li>Should <code>detail_sort: title</code> sort by raw title, normalized casefolded title, or a future title-sort key?</li>\n<li>Should a section with no details be allowed in canonical source so users can create sections before adding details?</li>\n<li>What should happen when a section is deleted: block while details exist, move details, or delete contained details after explicit confirmation?</li>\n</ul>\n"
}
