{
  "header": {
    "schema": "work_record_v2",
    "version": "blake2b-87c4c5f6c8467ea40b91d0c2e8a197fa",
    "generated_at_utc": "2026-03-20T13:50:43Z",
    "work_id": "00895",
    "count": 0
  },
  "work": {
    "work_id": "00895",
    "title": "doll moiré structures",
    "year": 2008,
    "year_display": "c. 2008",
    "series_ids": [
      "doll"
    ],
    "medium_type": "drawing",
    "medium_caption": "pencil on paper",
    "height_cm": 42.0,
    "width_cm": 59.4,
    "width_px": 1200,
    "height_px": 1685
  },
  "sections": []
}
