{
  "header": {
    "schema": "work_record_v3",
    "version": "blake2b-d6b3a7f7626899d808e78ae5b70ff0e3",
    "generated_at_utc": "2026-04-01T10:39:19Z",
    "work_id": "01420",
    "count": 0
  },
  "work": {
    "work_id": "01420",
    "title": "kylie grid map",
    "year": 2004,
    "year_display": "2004, 2011",
    "series_ids": [
      "093"
    ],
    "medium_type": "digital print",
    "medium_caption": "digital c-type print",
    "height_cm": 30.0,
    "width_cm": 30.0,
    "width_px": 3543,
    "height_px": 3543
  },
  "sections": []
}
