{
  "header": {
    "schema": "search_index_moments_v1",
    "scope": "moments",
    "version": "blake2b-2b32672726829ba18f0ab0721fc0f526",
    "generated_at_utc": "2026-07-15T09:18:20Z",
    "count": 56
  },
  "entries": [
    {
      "id": "d-20260215-000000-02a1a4",
      "kind": "doc",
      "title": "13 moments in october",
      "href": "/moments/?doc=d-20260215-000000-02a1a4",
      "search_terms": [
        "13 moments in october",
        "13",
        "moments",
        "in",
        "october",
        "d-20260215-000000-02a1a4"
      ],
      "search_text": "13 moments in october 13 moments in october d-20260215-000000-02a1a4"
    },
    {
      "id": "d-20260401-000000-2d7630",
      "kind": "doc",
      "title": "4 stories",
      "href": "/moments/?doc=d-20260401-000000-2d7630",
      "search_terms": [
        "4 stories",
        "4",
        "stories",
        "d-20260401-000000-2d7630"
      ],
      "search_text": "4 stories 4 stories d-20260401-000000-2d7630"
    },
    {
      "id": "d-20260215-000000-2d8bed",
      "kind": "doc",
      "title": "a beautiful route",
      "href": "/moments/?doc=d-20260215-000000-2d8bed",
      "search_terms": [
        "a beautiful route",
        "a",
        "beautiful",
        "route",
        "d-20260215-000000-2d8bed"
      ],
      "search_text": "a beautiful route a beautiful route d-20260215-000000-2d8bed"
    },
    {
      "id": "d-20260215-000000-cb455c",
      "kind": "doc",
      "title": "a dance",
      "href": "/moments/?doc=d-20260215-000000-cb455c",
      "search_terms": [
        "a dance",
        "a",
        "dance",
        "d-20260215-000000-cb455c"
      ],
      "search_text": "a dance a dance d-20260215-000000-cb455c"
    },
    {
      "id": "d-20260215-000000-7f201c",
      "kind": "doc",
      "title": "a doll story",
      "href": "/moments/?doc=d-20260215-000000-7f201c",
      "search_terms": [
        "a doll story",
        "a",
        "doll",
        "story",
        "d-20260215-000000-7f201c"
      ],
      "search_text": "a doll story a doll story d-20260215-000000-7f201c"
    },
    {
      "id": "d-20260215-000000-8c3fcc",
      "kind": "doc",
      "title": "a feeling of free will",
      "href": "/moments/?doc=d-20260215-000000-8c3fcc",
      "search_terms": [
        "a feeling of free will",
        "a",
        "feeling",
        "of",
        "free",
        "will",
        "d-20260215-000000-8c3fcc"
      ],
      "search_text": "a feeling of free will a feeling of free will d-20260215-000000-8c3fcc"
    },
    {
      "id": "d-20260215-000000-b5c568",
      "kind": "doc",
      "title": "a lemon tart poem",
      "href": "/moments/?doc=d-20260215-000000-b5c568",
      "search_terms": [
        "a lemon tart poem",
        "a",
        "lemon",
        "tart",
        "poem",
        "d-20260215-000000-b5c568"
      ],
      "search_text": "a lemon tart poem a lemon tart poem d-20260215-000000-b5c568"
    },
    {
      "id": "d-20260215-000000-e2a906",
      "kind": "doc",
      "title": "a light inside a flower",
      "href": "/moments/?doc=d-20260215-000000-e2a906",
      "search_terms": [
        "a light inside a flower",
        "a",
        "light",
        "inside",
        "flower",
        "d-20260215-000000-e2a906"
      ],
      "search_text": "a light inside a flower a light inside flower d-20260215-000000-e2a906"
    },
    {
      "id": "d-20260215-000000-c53845",
      "kind": "doc",
      "title": "a poem about love",
      "href": "/moments/?doc=d-20260215-000000-c53845",
      "search_terms": [
        "a poem about love",
        "a",
        "poem",
        "about",
        "love",
        "d-20260215-000000-c53845"
      ],
      "search_text": "a poem about love a poem about love d-20260215-000000-c53845"
    },
    {
      "id": "d-20260215-000000-d37a8a",
      "kind": "doc",
      "title": "a poem about purity",
      "href": "/moments/?doc=d-20260215-000000-d37a8a",
      "search_terms": [
        "a poem about purity",
        "a",
        "poem",
        "about",
        "purity",
        "d-20260215-000000-d37a8a"
      ],
      "search_text": "a poem about purity a poem about purity d-20260215-000000-d37a8a"
    },
    {
      "id": "d-20260215-000000-c6f320",
      "kind": "doc",
      "title": "a question",
      "href": "/moments/?doc=d-20260215-000000-c6f320",
      "search_terms": [
        "a question",
        "a",
        "question",
        "d-20260215-000000-c6f320"
      ],
      "search_text": "a question a question d-20260215-000000-c6f320"
    },
    {
      "id": "d-20260215-000000-ff9762",
      "kind": "doc",
      "title": "a selina",
      "href": "/moments/?doc=d-20260215-000000-ff9762",
      "search_terms": [
        "a selina",
        "a",
        "selina",
        "d-20260215-000000-ff9762"
      ],
      "search_text": "a selina a selina d-20260215-000000-ff9762"
    },
    {
      "id": "d-20260215-000000-f5f727",
      "kind": "doc",
      "title": "all the little cracks",
      "href": "/moments/?doc=d-20260215-000000-f5f727",
      "search_terms": [
        "all the little cracks",
        "all",
        "the",
        "little",
        "cracks",
        "d-20260215-000000-f5f727"
      ],
      "search_text": "all the little cracks all the little cracks d-20260215-000000-f5f727"
    },
    {
      "id": "d-20260215-000000-3b0cc8",
      "kind": "doc",
      "title": "angels",
      "href": "/moments/?doc=d-20260215-000000-3b0cc8",
      "search_terms": [
        "angels",
        "d-20260215-000000-3b0cc8"
      ],
      "search_text": "angels d-20260215-000000-3b0cc8"
    },
    {
      "id": "d-20260215-000000-6fd4d4",
      "kind": "doc",
      "title": "blue sky",
      "href": "/moments/?doc=d-20260215-000000-6fd4d4",
      "search_terms": [
        "blue sky",
        "blue",
        "sky",
        "d-20260215-000000-6fd4d4"
      ],
      "search_text": "blue sky blue sky d-20260215-000000-6fd4d4"
    },
    {
      "id": "d-20260215-000000-c5e2d1",
      "kind": "doc",
      "title": "boundary conditions",
      "href": "/moments/?doc=d-20260215-000000-c5e2d1",
      "search_terms": [
        "boundary conditions",
        "boundary",
        "conditions",
        "d-20260215-000000-c5e2d1"
      ],
      "search_text": "boundary conditions boundary conditions d-20260215-000000-c5e2d1"
    },
    {
      "id": "d-20260215-000000-c7da35",
      "kind": "doc",
      "title": "cascading waterfalls",
      "href": "/moments/?doc=d-20260215-000000-c7da35",
      "search_terms": [
        "cascading waterfalls",
        "cascading",
        "waterfalls",
        "d-20260215-000000-c7da35"
      ],
      "search_text": "cascading waterfalls cascading waterfalls d-20260215-000000-c7da35"
    },
    {
      "id": "d-20260215-000000-c218f2",
      "kind": "doc",
      "title": "circle",
      "href": "/moments/?doc=d-20260215-000000-c218f2",
      "search_terms": [
        "circle",
        "d-20260215-000000-c218f2"
      ],
      "search_text": "circle d-20260215-000000-c218f2"
    },
    {
      "id": "d-20260215-000000-216ea9",
      "kind": "doc",
      "title": "clouds",
      "href": "/moments/?doc=d-20260215-000000-216ea9",
      "search_terms": [
        "clouds",
        "d-20260215-000000-216ea9"
      ],
      "search_text": "clouds d-20260215-000000-216ea9"
    },
    {
      "id": "d-20260215-000000-d01949",
      "kind": "doc",
      "title": "compiled",
      "href": "/moments/?doc=d-20260215-000000-d01949",
      "search_terms": [
        "compiled",
        "d-20260215-000000-d01949"
      ],
      "search_text": "compiled d-20260215-000000-d01949"
    },
    {
      "id": "d-20260215-000000-2f1eb6",
      "kind": "doc",
      "title": "creatures who understand light",
      "href": "/moments/?doc=d-20260215-000000-2f1eb6",
      "search_terms": [
        "creatures who understand light",
        "creatures",
        "who",
        "understand",
        "light",
        "d-20260215-000000-2f1eb6"
      ],
      "search_text": "creatures who understand light creatures who understand light d-20260215-000000-2f1eb6"
    },
    {
      "id": "d-20260215-000000-1de7e9",
      "kind": "doc",
      "title": "dream sleep",
      "href": "/moments/?doc=d-20260215-000000-1de7e9",
      "search_terms": [
        "dream sleep",
        "dream",
        "sleep",
        "d-20260215-000000-1de7e9"
      ],
      "search_text": "dream sleep dream sleep d-20260215-000000-1de7e9"
    },
    {
      "id": "d-20260215-000000-09861a",
      "kind": "doc",
      "title": "droplets",
      "href": "/moments/?doc=d-20260215-000000-09861a",
      "search_terms": [
        "droplets",
        "d-20260215-000000-09861a"
      ],
      "search_text": "droplets d-20260215-000000-09861a"
    },
    {
      "id": "d-20260215-000000-bdb6fe",
      "kind": "doc",
      "title": "exit dreams",
      "href": "/moments/?doc=d-20260215-000000-bdb6fe",
      "search_terms": [
        "exit dreams",
        "exit",
        "dreams",
        "d-20260215-000000-bdb6fe"
      ],
      "search_text": "exit dreams exit dreams d-20260215-000000-bdb6fe"
    },
    {
      "id": "d-20260215-000000-ee27e1",
      "kind": "doc",
      "title": "healing forms",
      "href": "/moments/?doc=d-20260215-000000-ee27e1",
      "search_terms": [
        "healing forms",
        "healing",
        "forms",
        "d-20260215-000000-ee27e1"
      ],
      "search_text": "healing forms healing forms d-20260215-000000-ee27e1"
    },
    {
      "id": "d-20260215-000000-c04e75",
      "kind": "doc",
      "title": "hi honey",
      "href": "/moments/?doc=d-20260215-000000-c04e75",
      "search_terms": [
        "hi honey",
        "hi",
        "honey",
        "d-20260215-000000-c04e75"
      ],
      "search_text": "hi honey hi honey d-20260215-000000-c04e75"
    },
    {
      "id": "d-20260215-000000-382817",
      "kind": "doc",
      "title": "i felt my self sinking",
      "href": "/moments/?doc=d-20260215-000000-382817",
      "search_terms": [
        "i felt my self sinking",
        "i",
        "felt",
        "my",
        "self",
        "sinking",
        "d-20260215-000000-382817"
      ],
      "search_text": "i felt my self sinking i felt my self sinking d-20260215-000000-382817"
    },
    {
      "id": "d-20260215-000000-a15495",
      "kind": "doc",
      "title": "impenetrable",
      "href": "/moments/?doc=d-20260215-000000-a15495",
      "search_terms": [
        "impenetrable",
        "d-20260215-000000-a15495"
      ],
      "search_text": "impenetrable d-20260215-000000-a15495"
    },
    {
      "id": "d-20260215-000000-1d5e31",
      "kind": "doc",
      "title": "keys",
      "href": "/moments/?doc=d-20260215-000000-1d5e31",
      "search_terms": [
        "keys",
        "d-20260215-000000-1d5e31"
      ],
      "search_text": "keys d-20260215-000000-1d5e31"
    },
    {
      "id": "d-20260215-000000-33aca1",
      "kind": "doc",
      "title": "leaves",
      "href": "/moments/?doc=d-20260215-000000-33aca1",
      "search_terms": [
        "leaves",
        "d-20260215-000000-33aca1"
      ],
      "search_text": "leaves d-20260215-000000-33aca1"
    },
    {
      "id": "d-20260215-000000-da0340",
      "kind": "doc",
      "title": "little clear vessel",
      "href": "/moments/?doc=d-20260215-000000-da0340",
      "search_terms": [
        "little clear vessel",
        "little",
        "clear",
        "vessel",
        "d-20260215-000000-da0340"
      ],
      "search_text": "little clear vessel little clear vessel d-20260215-000000-da0340"
    },
    {
      "id": "d-20260215-000000-6ce9cf",
      "kind": "doc",
      "title": "lotus pond",
      "href": "/moments/?doc=d-20260215-000000-6ce9cf",
      "search_terms": [
        "lotus pond",
        "lotus",
        "pond",
        "d-20260215-000000-6ce9cf"
      ],
      "search_text": "lotus pond lotus pond d-20260215-000000-6ce9cf"
    },
    {
      "id": "d-20260215-000000-cd5956",
      "kind": "doc",
      "title": "memory",
      "href": "/moments/?doc=d-20260215-000000-cd5956",
      "search_terms": [
        "memory",
        "d-20260215-000000-cd5956"
      ],
      "search_text": "memory d-20260215-000000-cd5956"
    },
    {
      "id": "d-20260215-000000-30b26e",
      "kind": "doc",
      "title": "occasionally",
      "href": "/moments/?doc=d-20260215-000000-30b26e",
      "search_terms": [
        "occasionally",
        "d-20260215-000000-30b26e"
      ],
      "search_text": "occasionally d-20260215-000000-30b26e"
    },
    {
      "id": "d-20260215-000000-fb286f",
      "kind": "doc",
      "title": "particles",
      "href": "/moments/?doc=d-20260215-000000-fb286f",
      "search_terms": [
        "particles",
        "d-20260215-000000-fb286f"
      ],
      "search_text": "particles d-20260215-000000-fb286f"
    },
    {
      "id": "d-20260215-000000-22de5f",
      "kind": "doc",
      "title": "peace of mind",
      "href": "/moments/?doc=d-20260215-000000-22de5f",
      "search_terms": [
        "peace of mind",
        "peace",
        "of",
        "mind",
        "d-20260215-000000-22de5f"
      ],
      "search_text": "peace of mind peace of mind d-20260215-000000-22de5f"
    },
    {
      "id": "d-20260215-000000-d446d8",
      "kind": "doc",
      "title": "perfection of flowers",
      "href": "/moments/?doc=d-20260215-000000-d446d8",
      "search_terms": [
        "perfection of flowers",
        "perfection",
        "of",
        "flowers",
        "d-20260215-000000-d446d8"
      ],
      "search_text": "perfection of flowers perfection of flowers d-20260215-000000-d446d8"
    },
    {
      "id": "d-20260215-000000-4ddc7d",
      "kind": "doc",
      "title": "rose",
      "href": "/moments/?doc=d-20260215-000000-4ddc7d",
      "search_terms": [
        "rose",
        "d-20260215-000000-4ddc7d"
      ],
      "search_text": "rose d-20260215-000000-4ddc7d"
    },
    {
      "id": "d-20260215-000000-f81753",
      "kind": "doc",
      "title": "sadness love",
      "href": "/moments/?doc=d-20260215-000000-f81753",
      "search_terms": [
        "sadness love",
        "sadness",
        "love",
        "d-20260215-000000-f81753"
      ],
      "search_text": "sadness love sadness love d-20260215-000000-f81753"
    },
    {
      "id": "d-20260215-000000-e6723f",
      "kind": "doc",
      "title": "Samuel Beckett",
      "href": "/moments/?doc=d-20260215-000000-e6723f",
      "search_terms": [
        "samuel beckett",
        "samuel",
        "beckett",
        "d-20260215-000000-e6723f"
      ],
      "search_text": "samuel beckett samuel beckett d-20260215-000000-e6723f"
    },
    {
      "id": "d-20260215-000000-55070c",
      "kind": "doc",
      "title": "sleep",
      "href": "/moments/?doc=d-20260215-000000-55070c",
      "search_terms": [
        "sleep",
        "d-20260215-000000-55070c"
      ],
      "search_text": "sleep d-20260215-000000-55070c"
    },
    {
      "id": "d-20260215-000000-74539e",
      "kind": "doc",
      "title": "sleepy moments",
      "href": "/moments/?doc=d-20260215-000000-74539e",
      "search_terms": [
        "sleepy moments",
        "sleepy",
        "moments",
        "d-20260215-000000-74539e"
      ],
      "search_text": "sleepy moments sleepy moments d-20260215-000000-74539e"
    },
    {
      "id": "d-20260215-000000-ab1a77",
      "kind": "doc",
      "title": "snow",
      "href": "/moments/?doc=d-20260215-000000-ab1a77",
      "search_terms": [
        "snow",
        "d-20260215-000000-ab1a77"
      ],
      "search_text": "snow d-20260215-000000-ab1a77"
    },
    {
      "id": "d-20260215-000000-f1b2bb",
      "kind": "doc",
      "title": "the moment collector",
      "href": "/moments/?doc=d-20260215-000000-f1b2bb",
      "search_terms": [
        "the moment collector",
        "the",
        "moment",
        "collector",
        "d-20260215-000000-f1b2bb"
      ],
      "search_text": "the moment collector the moment collector d-20260215-000000-f1b2bb"
    },
    {
      "id": "d-20260215-000000-1caadb",
      "kind": "doc",
      "title": "the moon and the sun",
      "href": "/moments/?doc=d-20260215-000000-1caadb",
      "search_terms": [
        "the moon and the sun",
        "the",
        "moon",
        "and",
        "sun",
        "d-20260215-000000-1caadb"
      ],
      "search_text": "the moon and the sun the moon and sun d-20260215-000000-1caadb"
    },
    {
      "id": "d-20260215-000000-a56da5",
      "kind": "doc",
      "title": "the watch keeper",
      "href": "/moments/?doc=d-20260215-000000-a56da5",
      "search_terms": [
        "the watch keeper",
        "the",
        "watch",
        "keeper",
        "d-20260215-000000-a56da5"
      ],
      "search_text": "the watch keeper the watch keeper d-20260215-000000-a56da5"
    },
    {
      "id": "d-20260215-000000-6ea535",
      "kind": "doc",
      "title": "timeless",
      "href": "/moments/?doc=d-20260215-000000-6ea535",
      "search_terms": [
        "timeless",
        "d-20260215-000000-6ea535"
      ],
      "search_text": "timeless d-20260215-000000-6ea535"
    },
    {
      "id": "d-20260215-000000-cfd2a7",
      "kind": "doc",
      "title": "vessels",
      "href": "/moments/?doc=d-20260215-000000-cfd2a7",
      "search_terms": [
        "vessels",
        "d-20260215-000000-cfd2a7"
      ],
      "search_text": "vessels d-20260215-000000-cfd2a7"
    },
    {
      "id": "d-20260215-000000-b16a4f",
      "kind": "doc",
      "title": "warmth",
      "href": "/moments/?doc=d-20260215-000000-b16a4f",
      "search_terms": [
        "warmth",
        "d-20260215-000000-b16a4f"
      ],
      "search_text": "warmth d-20260215-000000-b16a4f"
    },
    {
      "id": "d-20260215-000000-c27a38",
      "kind": "doc",
      "title": "we are the vessel",
      "href": "/moments/?doc=d-20260215-000000-c27a38",
      "search_terms": [
        "we are the vessel",
        "we",
        "are",
        "the",
        "vessel",
        "d-20260215-000000-c27a38"
      ],
      "search_text": "we are the vessel we are the vessel d-20260215-000000-c27a38"
    },
    {
      "id": "d-20260215-000000-cb83ef",
      "kind": "doc",
      "title": "we make ghosts",
      "href": "/moments/?doc=d-20260215-000000-cb83ef",
      "search_terms": [
        "we make ghosts",
        "we",
        "make",
        "ghosts",
        "d-20260215-000000-cb83ef"
      ],
      "search_text": "we make ghosts we make ghosts d-20260215-000000-cb83ef"
    },
    {
      "id": "d-20260215-000000-7614a2",
      "kind": "doc",
      "title": "where",
      "href": "/moments/?doc=d-20260215-000000-7614a2",
      "search_terms": [
        "where",
        "d-20260215-000000-7614a2"
      ],
      "search_text": "where d-20260215-000000-7614a2"
    },
    {
      "id": "d-20260215-000000-24f316",
      "kind": "doc",
      "title": "where words end",
      "href": "/moments/?doc=d-20260215-000000-24f316",
      "search_terms": [
        "where words end",
        "where",
        "words",
        "end",
        "d-20260215-000000-24f316"
      ],
      "search_text": "where words end where words end d-20260215-000000-24f316"
    },
    {
      "id": "d-20260215-000000-b24b4f",
      "kind": "doc",
      "title": "will we leave residues",
      "href": "/moments/?doc=d-20260215-000000-b24b4f",
      "search_terms": [
        "will we leave residues",
        "will",
        "we",
        "leave",
        "residues",
        "d-20260215-000000-b24b4f"
      ],
      "search_text": "will we leave residues will we leave residues d-20260215-000000-b24b4f"
    },
    {
      "id": "d-20260215-000000-c518f2",
      "kind": "doc",
      "title": "winter",
      "href": "/moments/?doc=d-20260215-000000-c518f2",
      "search_terms": [
        "winter",
        "d-20260215-000000-c518f2"
      ],
      "search_text": "winter d-20260215-000000-c518f2"
    },
    {
      "id": "d-20260215-000000-6e2f83",
      "kind": "doc",
      "title": "without words",
      "href": "/moments/?doc=d-20260215-000000-6e2f83",
      "search_terms": [
        "without words",
        "without",
        "words",
        "d-20260215-000000-6e2f83"
      ],
      "search_text": "without words without words d-20260215-000000-6e2f83"
    }
  ]
}
